{"about_aboutduck.md":"a23a8134","about_aboutme.md":"094fe0ea","about_tale_helloworld.md":"537a9a80","about_tale_repeatthewheel.md":"c79daa0f","about_tale_rubberduckdebugging.md":"7ef19b5d","about_tale_masterandmain.md":"179e0452","bug_vuebug_bug01-nuxt3.md":"7222cccf","bug_index.md":"01a49a75","backend_express_express.md":"71005f20","backend_express_express_cors.md":"76b36420","backend_express_express_jwt.md":"1ebd8056","backend_express_express_mysql.md":"33edad21","backend_express_express_node_mysql.md":"0ed9417b","backend_express_express_route.md":"76d8a07f","backend_express_express_bcryptjs.md":"4e9d6490","backend_express_express_multer_avater.md":"db11b1f2","backend_express_express_multer_file.md":"2c6090c0","backend_express_express_static.md":"b9d1fce5","backend_express_nodemon.md":"53c9b3f7","backend_node_node.md":"68edab09","backend_node_node_fs.md":"e285b2d3","backend_node_node_http.md":"76da182e","backend_node_node_os.md":"81eb8aff","database_mysql_mysql.md":"e31c6ce8","database_sql_sql.md":"a9f0b8f2","database_sql_sql_delete.md":"bcc5a862","database_sql_sql_insert_into.md":"29777bb1","database_sql_sql_order.md":"a23eae10","database_sql_sql_select.md":"7f55ffe6","database_sql_sql_type.md":"d514a59d","database_sql_sql_update.md":"ff84ba77","database_sqlite_sqlite.md":"0b36b821","database_indexeddb_indexeddb.md":"a37614d4","database_indexeddb_localforage.md":"1cfc33fe","deploy_vitepress_favicon.md":"000d7a31","explore_2022_drag_drop.md":"9448bc2f","explore_2022_followmousemove.md":"00db0475","explore_2022_getmaincolor.md":"8a0b2fb0","explore_2022_create_npm.md":"f693adb5","explore_2022_index.md":"85c5c146","explore_project_index.md":"fca78bab","frontend_css_css.md":"b5b8f0c3","frontend_css_css3_compatibility.md":"a0f077e7","frontend_css_css3_media.md":"d72bf206","frontend_css_css3_note.md":"357c871a","frontend_css_css3_text.md":"845b92b4","frontend_css_css3_animation.md":"5c0f7873","frontend_css_css3_background.md":"9bb66f35","frontend_css_css3_transform.md":"9de023fd","frontend_css_css3_transition.md":"3cca5df5","frontend_css_css_codesnippet.md":"d8c59b60","frontend_css_css_note.md":"1b8904bb","frontend_css_css_selector.md":"ca727b29","frontend_css_css_sprite.md":"f6683c4f","frontend_css_css_var.md":"b01a96cc","frontend_css_layout_center.md":"3e4c9323","frontend_css_layout_flex.md":"50ffb9d4","frontend_css_layout_grid.md":"455cc959","frontend_extension_extension.md":"7c808aa9","frontend_frontend_helloworld.md":"af2a179f","frontend_frontend_learningpath.md":"0349163b","frontend_frontend_weapons.md":"87c83bdb","frontend_frontend_intro.md":"ab009b25","frontend_frontend_tutorial.md":"a6ca32c9","frontend_html_html.md":"934c5467","frontend_html_html5_webstorage.md":"ede8c16e","frontend_html_html_note.md":"fb8b2657","frontend_javascript_js_array.md":"e9763821","frontend_javascript_js_arraybatchesdelete.md":"136c6b32","frontend_javascript_js_arraydelete.md":"c5648987","frontend_javascript_js_arrayeach.md":"202bf38d","frontend_javascript_js_arrayfind.md":"680809d7","frontend_javascript_js_changetype.md":"e5e26597","frontend_javascript_js_codesnippet.md":"75142650","frontend_javascript_js_copy.md":"b45965f1","frontend_javascript_js_date.md":"773aba97","frontend_javascript_js_es6.md":"ed4a33aa","frontend_javascript_js_es6_class.md":"69e54dd5","frontend_javascript_js_mapset.md":"2ef1a40e","frontend_javascript_js_math.md":"3d1d0391","frontend_javascript_js_note.md":"46e51ede","frontend_javascript_js_object.md":"22fbe6c4","frontend_javascript_js_string.md":"4ccfc78e","frontend_javascript_js_events.md":"059e0705","frontend_javascript_js_module.md":"967f57cd","frontend_javascript_js_typeof.md":"c8aee2a1","frontend_javascript_javascript.md":"b4836258","frontend_nuxt_nuxt3.md":"c2ee2c8f","frontend_pwa_pwa.md":"6232af48","frontend_pwa_vite_pwa.md":"72dd3f4e","frontend_pwa_vue_pwa.md":"66817844","frontend_typescript_ts_array.md":"c0d07952","frontend_typescript_ts_funsion.md":"1ea2582e","frontend_typescript_ts_note.md":"f0c412d7","frontend_typescript_ts_assertion.md":"246237f8","frontend_typescript_ts_class.md":"8a068054","frontend_typescript_ts_declare.md":"27bf73f5","frontend_typescript_ts_enum.md":"e3d2bbd3","frontend_typescript_ts_generic.md":"0c79d25b","frontend_typescript_ts_interface.md":"463c5dd0","frontend_typescript_ts_objects.md":"fa250f11","frontend_typescript_ts_tuple.md":"41e7672a","frontend_typescript_ts_type.md":"a3ae138a","frontend_typescript_typescript.md":"fd2b3ede","frontend_vite_axios.md":"054b9702","frontend_vite_axios_vue2.md":"cf40565d","frontend_vite_axios_vue3.md":"43d96c86","frontend_vite_css_init.md":"3dc13071","frontend_vite_mobile.md":"ff8dfbbc","frontend_vite_pinia.md":"5c805409","frontend_vite_vite.md":"a6380075","frontend_vite_vite_sass.md":"2ec4499e","frontend_vite_vite_vuerouter.md":"f3d95d28","frontend_vite_vite_vuex.md":"736a52be","frontend_vite_vite_cors.md":"f77d34fc","frontend_vite_vite_env.md":"2c2bf913","frontend_vite_vuecli.md":"7818f311","frontend_vite_vuerouter.md":"8c59d941","frontend_vite_vue_scss.md":"8bd1c23d","frontend_vite_vuex.md":"09ba1e75","frontend_vue_vue.md":"9cfb0e92","frontend_vue_vue2_animation.md":"e470fec2","frontend_vue_vue2_components.md":"dc36726e","frontend_vue_vue2_computed.md":"801f95a2","frontend_vue_vue2_defineproperty.md":"b49fe518","frontend_vue_vue2_events.md":"12690180","frontend_vue_vue2_filters.md":"36878694","frontend_vue_vue2_keep-alive.md":"25d68c76","frontend_vue_vue2_life.md":"4bd8e165","frontend_vue_vue2_slot.md":"a3d487cc","frontend_vue_vue2_watch.md":"3760c206","frontend_vue_vue3.md":"4b6f0f19","frontend_vue_vue3_components.md":"40e9adfe","frontend_vue_vue3_computed.md":"acefcaff","frontend_vue_vue3_filters.md":"25b7386a","frontend_vue_vue3_ref.md":"334dfc46","frontend_vue_vue3_setup.md":"82a2d480","frontend_vue_vue3_watch.md":"04099bd7","frontend_vue_vue3_生命周期.md":"7a10a236","frontend_vue_vue_note.md":"d0ba0e7f","note_apifox.md":"1b30ed4a","note_eslint.md":"f732debb","note_git.md":"7742da97","note_git_remote.md":"0b2dd0e3","note_githubpagesname.md":"29006f6d","note_iconfont.md":"5e630ea9","note_judge_dark.md":"67a1db56","note_navicat.md":"3689a6ea","note_note_svg.md":"c99eac19","note_pcormoblie.md":"a08eaeb8","note_resizeobserver.md":"87a861ce","note_ssh.md":"078b01b4","note_svg.md":"26fbca99","note_shell_ip.md":"162bc542","note_vscode.md":"151d0e1d","note_vscode_plug.md":"5137a75c","note_vue_removeeventlistener.md":"29fdc6db","note_yarn.md":"2f9fd894","note_npm.md":"41858544","note_pnpm.md":"b7ea539d","project_xggame-minesweeper.md":"caf03329","project_xgnavigation.md":"b1013fec","project_index.md":"1800ba78","webspider_python_pythonfile.md":"f19bc96e","webspider_python_pythonnote.md":"5136763e","webspider_python_pythonnote_dictset.md":"2e4741b3","webspider_python_pythonnote_ifelse.md":"cc9408af","webspider_python_pythonnote_json.md":"44deddf2","webspider_python_pythonnote_list.md":"73f37ebd","webspider_python_pythonnote_str.md":"7e6d7bb5","webspider_python_pythonnote_type.md":"6a81624b","webspider_python_pythonnote_withas.md":"0c04fb24","webspider_python_pythonnote_def.md":"dfdc54eb","webspider_python_pythonnote_for.md":"595031c6","webspider_python_pythonnote_range.md":"d1f9f800","webspider_python_pythonnote_transition.md":"63b26caf","webspider_python_pythonnote_try.md":"b05c57a9","webspider_python_pythonnote_tuple.md":"81561c32","webspider_python_pythonnote_var.md":"8288f51e","webspider_python_python_install.md":"19febd14","webspider_python_python_intro.md":"3c28947c","webspider_python_continued.md":"b79633f0","webspider_spider_beautifulsoup.md":"9df17314","webspider_spider_ff_ajax.md":"5a5e05c1","webspider_spider_ff_cookie.md":"a077f618","webspider_spider_ff_ippool.md":"ed783354","webspider_spider_ff_referer.md":"61b1ccd4","webspider_spider_ff_useragent.md":"85b307ca","webspider_spider_ff_vpn.md":"03f27f68","webspider_spider_ff_verificationcode.md":"6bfc0d4f","webspider_spider_ff_sleep.md":"e273c463","webspider_spider_save_execel.md":"b38077f0","webspider_spider_save_mysql.md":"61ed2799","webspider_spider_save_sqlite.md":"edbfcc04","webspider_spider_save_txt.md":"45363e59","webspider_spider_getdata.md":"85cedb2e","webspider_spider_index.md":"f8910935","webspider_spider_requests.md":"be360038","index.md":"734d51f7"}
